qfeval_data/__init__.py
qfeval_data/data.py
qfeval_data/flattener.py
qfeval_data/plot.py
qfeval_data/util.py
qfeval_data/version.py
qfeval_data-0.1.1.dist-info/licenses/LICENSE
qfeval_data-0.1.1.dist-info/METADATA
qfeval_data-0.1.1.dist-info/WHEEL
qfeval_data-0.1.1.dist-info/top_level.txt
qfeval_data-0.1.1.dist-info/RECORD
