Metadata-Version: 2.4
Name: qfeval_data
Version: 0.1.1
Summary: Data structures for quantitative finance
Requires-Python: >=3.9
License-File: LICENSE
Requires-Dist: pandas
Requires-Dist: numpy
Requires-Dist: torch
Requires-Dist: qfeval-functions
Provides-Extra: plot
Requires-Dist: matplotlib; extra == "plot"
Dynamic: license-file
